{"type": "FeatureCollection", "features": [{"type": "Feature", "id": 0, "properties": {"tag": "MeToo", "text": "RT @nighatdad: I categorically deny the false and baseless allegations made against me by Ali Zafar on different TV shows regarding fake ac\u2026"}, "geometry": {"type": "Point", "coordinates": [73.07047271728516, 33.707679748535156]}}, {"type": "Feature", "id": 1, "properties": {"tag": "MeToo", "text": "#Metoo #Metooindia\nO' God save innocent men from fake molestation allegations... Save my country from fake accusers\u2026 https://t.co/hwNtX7xmjl"}, "geometry": {"type": "Point", "coordinates": [79.72701263427734, 22.493118286132812]}}, {"type": "Feature", "id": 2, "properties": {"tag": "MeToo", "text": "We need more journalists like @shazbkhanzdaGEO who knows exactly how to conduct an interview based on a very sensit\u2026 https://t.co/7J7NuNWWnj"}, "geometry": {"type": "Point", "coordinates": [73.07047271728516, 33.707679748535156]}}, {"type": "Feature", "id": 3, "properties": {"tag": "MeToo", "text": "#nonprofits need to be at the forefront of the #metoo movement. Learn how to address the pervasive issue of sexual\u2026 https://t.co/A8MucgQ9S2"}, "geometry": {"type": "Point", "coordinates": [-97.74298858642578, 30.267589569091797]}}, {"type": "Feature", "id": 4, "properties": {"tag": "MeToo", "text": "RT @ChatByCC: @Rockprincess818 \u201cMy name is Hunter Kelly. I am 21 years old. I was sexually assaulted by Mayor Pete Buttigieg. I didn\u2019t know\u2026"}, "geometry": {"type": "Point", "coordinates": [-122.41963958740234, 37.77711868286133]}}, {"type": "Feature", "id": 5, "properties": {"tag": "MeToo", "text": "RT @PrisonPlanet: Presidential candidate Mayor Pete Buttigieg is facing a potential #MeToo scandal after a Michigan man accused Buttigieg o\u2026"}, "geometry": {"type": "Point", "coordinates": [-77.83875274658203, 40.89651107788086]}}, {"type": "Feature", "id": 6, "properties": {"tag": "MeToo", "text": "RT @RealRCMaxwell: It's truly disgusting how Democrats are using #metoo to tear down American scholar and Black icon Clarence Thomas.\nhttps\u2026"}, "geometry": {"type": "Point", "coordinates": [-114.46959686279297, 42.556190490722656]}}, {"type": "Feature", "id": 7, "properties": {"tag": "MeToo", "text": "Pelosi stands by Gropey Joe Biden\n\nSays accusations against Biden DO NOT disqualify him from being President\n\nSo mu\u2026 https://t.co/nDmws7ZyvL"}, "geometry": {"type": "Point", "coordinates": [-98.98998260498047, 39.495914459228516]}}, {"type": "Feature", "id": 8, "properties": {"tag": "MeToo", "text": "RT @ChatByCC: \u201cMy name is Hunter Kelly. I am 21 years old. I was sexually assaulted by Mayor Pete Buttigieg. I didn\u2019t know who he was back\u2026"}, "geometry": {"type": "Point", "coordinates": [-86.28179931640625, 39.919803619384766]}}, {"type": "Feature", "id": 9, "properties": {"tag": "MeToo", "text": "RT @j_gelling: @ChatByCC @Rockprincess818 I'm not joining #MeToo but as with all these allegations we need to hear from the victim and the\u2026"}, "geometry": {"type": "Point", "coordinates": [-77.83875274658203, 40.89651107788086]}}, {"type": "Feature", "id": 10, "properties": {"tag": "MeToo", "text": "@hunterkelly  Thank you for your testimony of  a horrible experience.  \n#Buttigieg  is a non-starter and you just p\u2026 https://t.co/PrTL6n7rRb"}, "geometry": {"type": "Point", "coordinates": [-92.4778823852539, 38.36796569824219]}}, {"type": "Feature", "id": 11, "properties": {"tag": "MeToo", "text": "RT @FaerieWhings: A #MeToo story in the works.\n\nI hope Hunter heals. \n\nhttps://t.co/reIkzxTvt6"}, "geometry": {"type": "Point", "coordinates": [-84.39111328125, 33.74831008911133]}}, {"type": "Feature", "id": 12, "properties": {"tag": "MeToo", "text": "RT @OGMurphy1: I AM ASHAMED BY BREXIT..\n\nThe way migrants were used as a scapegoat for our own government's economic failure;\n\nThe way chea\u2026"}, "geometry": {"type": "Point", "coordinates": [9.181779861450195, 45.467960357666016]}}, {"type": "Feature", "id": 13, "properties": {"tag": "MeToo", "text": "RT @ChatByCC: @Rockprincess818 \u201cMy name is Hunter Kelly. I am 21 years old. I was sexually assaulted by Mayor Pete Buttigieg. I didn\u2019t know\u2026"}, "geometry": {"type": "Point", "coordinates": [-84.39111328125, 33.74831008911133]}}, {"type": "Feature", "id": 14, "properties": {"tag": "MeToo", "text": "I\u2019m curious if @GeorgeTakei will be as hard on #PeteButtigieg as he was on Brett Kavanaugh. #metoo right Sulu?? \u201cal\u2026 https://t.co/5wwqW49mQn"}, "geometry": {"type": "Point", "coordinates": [-82.47222137451172, 28.49258041381836]}}, {"type": "Feature", "id": 15, "properties": {"tag": "MeToo", "text": "RT @PrisonPlanet: Presidential candidate Mayor Pete Buttigieg is facing a potential #MeToo scandal after a Michigan man accused Buttigieg o\u2026"}, "geometry": {"type": "Point", "coordinates": [-0.12721000611782074, 51.50642013549805]}}, {"type": "Feature", "id": 16, "properties": {"tag": "MeToo", "text": "When you see someone in a bar being creepy to guests or staff, the worst thing you can do Is nothing -- by bartende\u2026 https://t.co/PledO0zWBd"}, "geometry": {"type": "Point", "coordinates": [-78.64266967773438, 35.7855110168457]}}, {"type": "Feature", "id": 17, "properties": {"tag": "MeToo", "text": "RT @morethanmySLE: If it wasn't for the bravery of @TaranaBurke &amp; @Alyssa_Milano I would have NEVER shared my #metoo story.\n\nListening to @\u2026"}, "geometry": {"type": "Point", "coordinates": [-73.96624755859375, 40.7834358215332]}}, {"type": "Feature", "id": 18, "properties": {"tag": "MeToo", "text": "RT @morethanmySLE: \u201cIt\u2019s very healing to share your story, &amp; the only way that we can prevent this from happening, is to talk about it, &amp; k\u2026"}, "geometry": {"type": "Point", "coordinates": [-73.96624755859375, 40.7834358215332]}}, {"type": "Feature", "id": 19, "properties": {"tag": "MeToo", "text": "RT @RichGas8: @TBInvestigation Another crazy ass liberal....every mass shooting since President Trump was elected has been a liberal. Every\u2026"}, "geometry": {"type": "Point", "coordinates": [-80.2874984741211, 40.86030197143555]}}, {"type": "Feature", "id": 20, "properties": {"tag": "MeToo", "text": "Little Did I Know by Songbird inspired by #MichealJackson and #MeToo Sherri\u2019s #lies https://t.co/kfxfs75psl for\u2026 https://t.co/HbNKyWfrNX"}, "geometry": {"type": "Point", "coordinates": [-79.38543701171875, 43.64868927001953]}}, {"type": "Feature", "id": 21, "properties": {"tag": "MeToo", "text": "RT @morethanmySLE: If it wasn't for the bravery of @TaranaBurke &amp; @Alyssa_Milano I would have NEVER shared my #metoo story.\n\nListening to @\u2026"}, "geometry": {"type": "Point", "coordinates": [-119.61752319335938, 37.25510025024414]}}, {"type": "Feature", "id": 22, "properties": {"tag": "MeToo", "text": "RT @ScottRickhoff: Democrat Nobody Pete #Buttplug Accused of Sexual Assault by 21-Year-Old from Michigan. #Metoo #WalkAwayFromDemocrats #Wa\u2026"}, "geometry": {"type": "Point", "coordinates": [-92.8105697631836, 45.05670166015625]}}, {"type": "Feature", "id": 23, "properties": {"tag": "MeToo", "text": "Interesting that of your handful of likes, all but one are super supportive of Bernie and you have a whopping 1 act\u2026 https://t.co/kuXzwtnEBg"}, "geometry": {"type": "Point", "coordinates": [-89.64360046386719, 39.801048278808594]}}, {"type": "Feature", "id": 24, "properties": {"tag": "MeToo", "text": "Democrats allowed #MeToo to run untethered and unchecked when it benefited them. Anyone wanna place bets on how qui\u2026 https://t.co/0qE5IrmZMc"}, "geometry": {"type": "Point", "coordinates": [-91.1167984008789, 48.04707717895508]}}, {"type": "Feature", "id": 25, "properties": {"tag": "MeToo", "text": "RT @ScottRickhoff: Democrat Nobody Pete #Buttplug Accused of Sexual Assault by 21-Year-Old from Michigan. #Metoo #WalkAwayFromDemocrats #Wa\u2026"}, "geometry": {"type": "Point", "coordinates": [-83.4445571899414, 32.64833068847656]}}, {"type": "Feature", "id": 26, "properties": {"tag": "MeToo", "text": "RT @TheAbdullahKhan: First of all I think Shahzeb Khanzada deserves credit for conducting a highly professional interview with Meesha Shafi\u2026"}, "geometry": {"type": "Point", "coordinates": [73.07047271728516, 33.707679748535156]}}, {"type": "Feature", "id": 27, "properties": {"tag": "MeToo", "text": "RT @FullStopFdn: \"The underlying driver of sexual harassment in workplaces is power and the misuse of power, and because different workplac\u2026"}, "geometry": {"type": "Point", "coordinates": [144.53526306152344, -22.575700759887695]}}, {"type": "Feature", "id": 28, "properties": {"tag": "MeToo", "text": "@SuperPatriotone Wow, the #MeToo movement should be all over this.\n\nWhere is @Alyssa_Milano on this and did she ask\u2026 https://t.co/3FHTRnFdpd"}, "geometry": {"type": "Point", "coordinates": [-86.34304809570312, 35.84300231933594]}}, {"type": "Feature", "id": 29, "properties": {"tag": "MeToo", "text": "RT @FaerieWhings: A #MeToo story in the works.\n\nI hope Hunter heals. \n\nhttps://t.co/reIkzxTvt6"}, "geometry": {"type": "Point", "coordinates": [-118.472325, 34.2276600003532]}}, {"type": "Feature", "id": 30, "properties": {"tag": "MeToo", "text": "@darklordjournal @AspcraAdInferi Nah, not really. #MeToo"}, "geometry": {"type": "Point", "coordinates": [-150.05264282226562, 62.206478118896484]}}, {"type": "Feature", "id": 31, "properties": {"tag": "MeToo", "text": "Mayor Pete Hit With #MeToo Allegation of Sexual Assault https://t.co/M0tWnxJ9hw"}, "geometry": {"type": "Point", "coordinates": [-85.2876205444336, 37.5272331237793]}}, {"type": "Feature", "id": 32, "properties": {"tag": "MeToo", "text": "Democrat Nobody Pete #Buttplug Accused of Sexual Assault by 21-Year-Old from Michigan. #Metoo\u2026 https://t.co/SQ2K64c8tk"}, "geometry": {"type": "Point", "coordinates": [-98.98998260498047, 39.495914459228516]}}, {"type": "Feature", "id": 33, "properties": {"tag": "MeToo", "text": "RT @OGMurphy1: I AM ASHAMED BY BREXIT..\n\nThe way migrants were used as a scapegoat for our own government's economic failure;\n\nThe way chea\u2026"}, "geometry": {"type": "Point", "coordinates": [-2.5505640506744385, 53.9438362121582]}}, {"type": "Feature", "id": 34, "properties": {"tag": "MeToo", "text": "RT @ChatByCC: \u201cMy name is Hunter Kelly. I am 21 years old. I was sexually assaulted by Mayor Pete Buttigieg. I didn\u2019t know who he was back\u2026"}, "geometry": {"type": "Point", "coordinates": [-77.83875274658203, 40.89651107788086]}}, {"type": "Feature", "id": 35, "properties": {"tag": "MeToo", "text": "@gatewaypundit #metoo  - time to treat ol Pete like Kavanaugh"}, "geometry": {"type": "Point", "coordinates": [-85.73513793945312, 44.86261749267578]}}, {"type": "Feature", "id": 36, "properties": {"tag": "MeToo", "text": "RT @FreedomForumIns: \u201cIn late 2017 when #MeToo revelations exposed sexual harassment &amp; misconduct in many media organizations, we immediate\u2026"}, "geometry": {"type": "Point", "coordinates": [-89.73674011230469, 44.64178466796875]}}, {"type": "Feature", "id": 37, "properties": {"tag": "MeToo", "text": "@NickANigro @worldincommon @thesweatytuna @MrFesser @StarTribune The Vikings were known as rapists and pillagers wh\u2026 https://t.co/MG3wnKA4e6"}, "geometry": {"type": "Point", "coordinates": [-94.19837188720703, 46.34935760498047]}}, {"type": "Feature", "id": 38, "properties": {"tag": "MeToo", "text": "@diamondsnjeans @RonHall46 At last! An opportunity for me to say:\n\n     MeToo"}, "geometry": {"type": "Point", "coordinates": [-0.12721000611782074, 51.50642013549805]}}, {"type": "Feature", "id": 39, "properties": {"tag": "MeToo", "text": "Why people speaking in favour of PTM and Meesha shafi are the same ? "}, "geometry": {"type": "Point", "coordinates": [74.30348205566406, 31.53944969177246]}}, {"type": "Feature", "id": 40, "properties": {"tag": "MeToo", "text": "RT @ChatByCC: @Rockprincess818 \u201cMy name is Hunter Kelly. I am 21 years old. I was sexually assaulted by Mayor Pete Buttigieg. I didn\u2019t know\u2026"}, "geometry": {"type": "Point", "coordinates": [-119.61752319335938, 37.25510025024414]}}, {"type": "Feature", "id": 41, "properties": {"tag": "MeToo", "text": "RT @snowball1926: Here We go...True, not true?  Who are the @TheDemocrats going to believe.  What about the #MeToo movement?\n\n\"I was sexual\u2026"}, "geometry": {"type": "Point", "coordinates": [-99.3330307006836, 31.46275520324707]}}, {"type": "Feature", "id": 42, "properties": {"tag": "MeToo", "text": "RT @PrisonPlanet: Presidential candidate Mayor Pete Buttigieg is facing a potential #MeToo scandal after a Michigan man accused Buttigieg o\u2026"}, "geometry": {"type": "Point", "coordinates": [-98.98998260498047, 39.495914459228516]}}, {"type": "Feature", "id": 43, "properties": {"tag": "MeToo", "text": "@Maria_Memon @itsmeeshashafi Hahaha. This PTM and Metoo are tge new kewl to support"}, "geometry": {"type": "Point", "coordinates": [67.03437042236328, 24.92671012878418]}}, {"type": "Feature", "id": 44, "properties": {"tag": "MeToo", "text": "RT @EmHarriss: Whenever I hear men say, \u201cever since the #metoo era, we men have to be so careful\u201d .... I\u2019m like, be careful of what? Not ha\u2026"}, "geometry": {"type": "Point", "coordinates": [-2.4750399589538574, 52.7036018371582]}}, {"type": "Feature", "id": 45, "properties": {"tag": "MeToo", "text": "RT @ChatByCC: @Rockprincess818 \u201cMy name is Hunter Kelly. I am 21 years old. I was sexually assaulted by Mayor Pete Buttigieg. I didn\u2019t know\u2026"}, "geometry": {"type": "Point", "coordinates": [-79.18537902832031, 35.53935241699219]}}, {"type": "Feature", "id": 46, "properties": {"tag": "MeToo", "text": "RT @HtownDood: What do you make of this?\n#metoo?\nhttps://t.co/70LpXjeYvI"}, "geometry": {"type": "Point", "coordinates": [-99.3330307006836, 31.46275520324707]}}, {"type": "Feature", "id": 47, "properties": {"tag": "MeToo", "text": "Why women should have equal opportunities and rights in all countries worldwide: https://t.co/9dwQZEKSUv\n#feminism\u2026 https://t.co/FETc3z6GLk"}, "geometry": {"type": "Point", "coordinates": [26.282997131347656, 64.51988983154297]}}, {"type": "Feature", "id": 48, "properties": {"tag": "MeToo", "text": "\u2018MeToo\u2019 Hysteria: Handshakes In The Workplace Could Be Next On Chopping Block https://t.co/u7uvaWswxf"}, "geometry": {"type": "Point", "coordinates": [-119.61752319335938, 37.25510025024414]}}, {"type": "Feature", "id": 49, "properties": {"tag": "MeToo", "text": "RT @ChatByCC: @Rockprincess818 \u201cMy name is Hunter Kelly. I am 21 years old. I was sexually assaulted by Mayor Pete Buttigieg. I didn\u2019t know\u2026"}, "geometry": {"type": "Point", "coordinates": [-82.40010833740234, 34.848270416259766]}}, {"type": "Feature", "id": 50, "properties": {"tag": "MeToo", "text": "She says I'll check those msgs again ,wow chutyaa smjhaa hua hai awaam ko \nShe is fake Ali Zafar showed us proof wh\u2026 https://t.co/CWQer36z8m"}, "geometry": {"type": "Point", "coordinates": [68.80183410644531, 29.354202270507812]}}, {"type": "Feature", "id": 51, "properties": {"tag": "MeToo", "text": "RT @wkamaubell: The conversation w/ @emilyjoypoetry and her story of being abused in a megachurch that led her to create #ChurchToo (which\u2026"}, "geometry": {"type": "Point", "coordinates": [-83.53626251220703, 41.65380859375]}}, {"type": "Feature", "id": 52, "properties": {"tag": "MeToo", "text": "RT @nighatdad: I categorically deny the false and baseless allegations made against me by Ali Zafar on different TV shows regarding fake ac\u2026"}, "geometry": {"type": "Point", "coordinates": [73.07047271728516, 33.707679748535156]}}, {"type": "Feature", "id": 53, "properties": {"tag": "MeToo", "text": "#Metoo #Metooindia\nO' God save innocent men from fake molestation allegations... Save my country from fake accusers\u2026 https://t.co/hwNtX7xmjl"}, "geometry": {"type": "Point", "coordinates": [79.72701263427734, 22.493118286132812]}}, {"type": "Feature", "id": 54, "properties": {"tag": "MeToo", "text": "We need more journalists like @shazbkhanzdaGEO who knows exactly how to conduct an interview based on a very sensit\u2026 https://t.co/7J7NuNWWnj"}, "geometry": {"type": "Point", "coordinates": [73.07047271728516, 33.707679748535156]}}, {"type": "Feature", "id": 55, "properties": {"tag": "MeToo", "text": "#nonprofits need to be at the forefront of the #metoo movement. Learn how to address the pervasive issue of sexual\u2026 https://t.co/A8MucgQ9S2"}, "geometry": {"type": "Point", "coordinates": [-97.74298858642578, 30.267589569091797]}}, {"type": "Feature", "id": 56, "properties": {"tag": "MeToo", "text": "RT @ChatByCC: @Rockprincess818 \u201cMy name is Hunter Kelly. I am 21 years old. I was sexually assaulted by Mayor Pete Buttigieg. I didn\u2019t know\u2026"}, "geometry": {"type": "Point", "coordinates": [-122.41963958740234, 37.77711868286133]}}, {"type": "Feature", "id": 57, "properties": {"tag": "MeToo", "text": "RT @PrisonPlanet: Presidential candidate Mayor Pete Buttigieg is facing a potential #MeToo scandal after a Michigan man accused Buttigieg o\u2026"}, "geometry": {"type": "Point", "coordinates": [-77.83875274658203, 40.89651107788086]}}, {"type": "Feature", "id": 58, "properties": {"tag": "MeToo", "text": "RT @RealRCMaxwell: It's truly disgusting how Democrats are using #metoo to tear down American scholar and Black icon Clarence Thomas.\nhttps\u2026"}, "geometry": {"type": "Point", "coordinates": [-114.46959686279297, 42.556190490722656]}}, {"type": "Feature", "id": 59, "properties": {"tag": "MeToo", "text": "Pelosi stands by Gropey Joe Biden\n\nSays accusations against Biden DO NOT disqualify him from being President\n\nSo mu\u2026 https://t.co/nDmws7ZyvL"}, "geometry": {"type": "Point", "coordinates": [-98.98998260498047, 39.495914459228516]}}, {"type": "Feature", "id": 60, "properties": {"tag": "MeToo", "text": "RT @ChatByCC: \u201cMy name is Hunter Kelly. I am 21 years old. I was sexually assaulted by Mayor Pete Buttigieg. I didn\u2019t know who he was back\u2026"}, "geometry": {"type": "Point", "coordinates": [-86.28179931640625, 39.919803619384766]}}, {"type": "Feature", "id": 61, "properties": {"tag": "MeToo", "text": "RT @j_gelling: @ChatByCC @Rockprincess818 I'm not joining #MeToo but as with all these allegations we need to hear from the victim and the\u2026"}, "geometry": {"type": "Point", "coordinates": [-77.83875274658203, 40.89651107788086]}}, {"type": "Feature", "id": 62, "properties": {"tag": "MeToo", "text": "@hunterkelly  Thank you for your testimony of  a horrible experience.  \n#Buttigieg  is a non-starter and you just p\u2026 https://t.co/PrTL6n7rRb"}, "geometry": {"type": "Point", "coordinates": [-92.4778823852539, 38.36796569824219]}}, {"type": "Feature", "id": 63, "properties": {"tag": "MeToo", "text": "RT @FaerieWhings: A #MeToo story in the works.\n\nI hope Hunter heals. \n\nhttps://t.co/reIkzxTvt6"}, "geometry": {"type": "Point", "coordinates": [-84.39111328125, 33.74831008911133]}}, {"type": "Feature", "id": 64, "properties": {"tag": "MeToo", "text": "RT @OGMurphy1: I AM ASHAMED BY BREXIT..\n\nThe way migrants were used as a scapegoat for our own government's economic failure;\n\nThe way chea\u2026"}, "geometry": {"type": "Point", "coordinates": [9.181779861450195, 45.467960357666016]}}, {"type": "Feature", "id": 65, "properties": {"tag": "MeToo", "text": "RT @ChatByCC: @Rockprincess818 \u201cMy name is Hunter Kelly. I am 21 years old. I was sexually assaulted by Mayor Pete Buttigieg. I didn\u2019t know\u2026"}, "geometry": {"type": "Point", "coordinates": [-84.39111328125, 33.74831008911133]}}, {"type": "Feature", "id": 66, "properties": {"tag": "MeToo", "text": "I\u2019m curious if @GeorgeTakei will be as hard on #PeteButtigieg as he was on Brett Kavanaugh. #metoo right Sulu?? \u201cal\u2026 https://t.co/5wwqW49mQn"}, "geometry": {"type": "Point", "coordinates": [-82.47222137451172, 28.49258041381836]}}, {"type": "Feature", "id": 67, "properties": {"tag": "MeToo", "text": "RT @PrisonPlanet: Presidential candidate Mayor Pete Buttigieg is facing a potential #MeToo scandal after a Michigan man accused Buttigieg o\u2026"}, "geometry": {"type": "Point", "coordinates": [-0.12721000611782074, 51.50642013549805]}}, {"type": "Feature", "id": 68, "properties": {"tag": "MeToo", "text": "When you see someone in a bar being creepy to guests or staff, the worst thing you can do Is nothing -- by bartende\u2026 https://t.co/PledO0zWBd"}, "geometry": {"type": "Point", "coordinates": [-78.64266967773438, 35.7855110168457]}}, {"type": "Feature", "id": 69, "properties": {"tag": "MeToo", "text": "RT @morethanmySLE: If it wasn't for the bravery of @TaranaBurke &amp; @Alyssa_Milano I would have NEVER shared my #metoo story.\n\nListening to @\u2026"}, "geometry": {"type": "Point", "coordinates": [-73.96624755859375, 40.7834358215332]}}, {"type": "Feature", "id": 70, "properties": {"tag": "MeToo", "text": "RT @morethanmySLE: \u201cIt\u2019s very healing to share your story, &amp; the only way that we can prevent this from happening, is to talk about it, &amp; k\u2026"}, "geometry": {"type": "Point", "coordinates": [-73.96624755859375, 40.7834358215332]}}, {"type": "Feature", "id": 71, "properties": {"tag": "MeToo", "text": "RT @RichGas8: @TBInvestigation Another crazy ass liberal....every mass shooting since President Trump was elected has been a liberal. Every\u2026"}, "geometry": {"type": "Point", "coordinates": [-80.2874984741211, 40.86030197143555]}}, {"type": "Feature", "id": 72, "properties": {"tag": "MeToo", "text": "Little Did I Know by Songbird inspired by #MichealJackson and #MeToo Sherri\u2019s #lies https://t.co/kfxfs75psl for\u2026 https://t.co/HbNKyWfrNX"}, "geometry": {"type": "Point", "coordinates": [-79.38543701171875, 43.64868927001953]}}, {"type": "Feature", "id": 73, "properties": {"tag": "MeToo", "text": "RT @morethanmySLE: If it wasn't for the bravery of @TaranaBurke &amp; @Alyssa_Milano I would have NEVER shared my #metoo story.\n\nListening to @\u2026"}, "geometry": {"type": "Point", "coordinates": [-119.61752319335938, 37.25510025024414]}}, {"type": "Feature", "id": 74, "properties": {"tag": "MeToo", "text": "RT @ScottRickhoff: Democrat Nobody Pete #Buttplug Accused of Sexual Assault by 21-Year-Old from Michigan. #Metoo #WalkAwayFromDemocrats #Wa\u2026"}, "geometry": {"type": "Point", "coordinates": [-92.8105697631836, 45.05670166015625]}}, {"type": "Feature", "id": 75, "properties": {"tag": "MeToo", "text": "Interesting that of your handful of likes, all but one are super supportive of Bernie and you have a whopping 1 act\u2026 https://t.co/kuXzwtnEBg"}, "geometry": {"type": "Point", "coordinates": [-89.64360046386719, 39.801048278808594]}}, {"type": "Feature", "id": 76, "properties": {"tag": "MeToo", "text": "Democrats allowed #MeToo to run untethered and unchecked when it benefited them. Anyone wanna place bets on how qui\u2026 https://t.co/0qE5IrmZMc"}, "geometry": {"type": "Point", "coordinates": [-91.1167984008789, 48.04707717895508]}}, {"type": "Feature", "id": 77, "properties": {"tag": "MeToo", "text": "RT @ScottRickhoff: Democrat Nobody Pete #Buttplug Accused of Sexual Assault by 21-Year-Old from Michigan. #Metoo #WalkAwayFromDemocrats #Wa\u2026"}, "geometry": {"type": "Point", "coordinates": [-83.4445571899414, 32.64833068847656]}}, {"type": "Feature", "id": 78, "properties": {"tag": "MeToo", "text": "RT @TheAbdullahKhan: First of all I think Shahzeb Khanzada deserves credit for conducting a highly professional interview with Meesha Shafi\u2026"}, "geometry": {"type": "Point", "coordinates": [73.07047271728516, 33.707679748535156]}}, {"type": "Feature", "id": 79, "properties": {"tag": "MeToo", "text": "RT @FullStopFdn: \"The underlying driver of sexual harassment in workplaces is power and the misuse of power, and because different workplac\u2026"}, "geometry": {"type": "Point", "coordinates": [144.53526306152344, -22.575700759887695]}}, {"type": "Feature", "id": 80, "properties": {"tag": "MeToo", "text": "@SuperPatriotone Wow, the #MeToo movement should be all over this.\n\nWhere is @Alyssa_Milano on this and did she ask\u2026 https://t.co/3FHTRnFdpd"}, "geometry": {"type": "Point", "coordinates": [-86.34304809570312, 35.84300231933594]}}, {"type": "Feature", "id": 81, "properties": {"tag": "MeToo", "text": "RT @FaerieWhings: A #MeToo story in the works.\n\nI hope Hunter heals. \n\nhttps://t.co/reIkzxTvt6"}, "geometry": {"type": "Point", "coordinates": [-118.472325, 34.2276600003532]}}, {"type": "Feature", "id": 82, "properties": {"tag": "MeToo", "text": "@darklordjournal @AspcraAdInferi Nah, not really. #MeToo"}, "geometry": {"type": "Point", "coordinates": [-150.05264282226562, 62.206478118896484]}}, {"type": "Feature", "id": 83, "properties": {"tag": "MeToo", "text": "Mayor Pete Hit With #MeToo Allegation of Sexual Assault https://t.co/M0tWnxJ9hw"}, "geometry": {"type": "Point", "coordinates": [-85.2876205444336, 37.5272331237793]}}, {"type": "Feature", "id": 84, "properties": {"tag": "MeToo", "text": "Democrat Nobody Pete #Buttplug Accused of Sexual Assault by 21-Year-Old from Michigan. #Metoo\u2026 https://t.co/SQ2K64c8tk"}, "geometry": {"type": "Point", "coordinates": [-98.98998260498047, 39.495914459228516]}}, {"type": "Feature", "id": 85, "properties": {"tag": "MeToo", "text": "RT @OGMurphy1: I AM ASHAMED BY BREXIT..\n\nThe way migrants were used as a scapegoat for our own government's economic failure;\n\nThe way chea\u2026"}, "geometry": {"type": "Point", "coordinates": [-2.5505640506744385, 53.9438362121582]}}, {"type": "Feature", "id": 86, "properties": {"tag": "MeToo", "text": "RT @ChatByCC: \u201cMy name is Hunter Kelly. I am 21 years old. I was sexually assaulted by Mayor Pete Buttigieg. I didn\u2019t know who he was back\u2026"}, "geometry": {"type": "Point", "coordinates": [-77.83875274658203, 40.89651107788086]}}, {"type": "Feature", "id": 87, "properties": {"tag": "MeToo", "text": "@gatewaypundit #metoo  - time to treat ol Pete like Kavanaugh"}, "geometry": {"type": "Point", "coordinates": [-85.73513793945312, 44.86261749267578]}}, {"type": "Feature", "id": 88, "properties": {"tag": "MeToo", "text": "RT @FreedomForumIns: \u201cIn late 2017 when #MeToo revelations exposed sexual harassment &amp; misconduct in many media organizations, we immediate\u2026"}, "geometry": {"type": "Point", "coordinates": [-89.73674011230469, 44.64178466796875]}}, {"type": "Feature", "id": 89, "properties": {"tag": "MeToo", "text": "@NickANigro @worldincommon @thesweatytuna @MrFesser @StarTribune The Vikings were known as rapists and pillagers wh\u2026 https://t.co/MG3wnKA4e6"}, "geometry": {"type": "Point", "coordinates": [-94.19837188720703, 46.34935760498047]}}, {"type": "Feature", "id": 90, "properties": {"tag": "MeToo", "text": "@diamondsnjeans @RonHall46 At last! An opportunity for me to say:\n\n     MeToo"}, "geometry": {"type": "Point", "coordinates": [-0.12721000611782074, 51.50642013549805]}}, {"type": "Feature", "id": 91, "properties": {"tag": "MeToo", "text": "Why people speaking in favour of PTM and Meesha shafi are the same ? "}, "geometry": {"type": "Point", "coordinates": [74.30348205566406, 31.53944969177246]}}, {"type": "Feature", "id": 92, "properties": {"tag": "MeToo", "text": "RT @ChatByCC: @Rockprincess818 \u201cMy name is Hunter Kelly. I am 21 years old. I was sexually assaulted by Mayor Pete Buttigieg. I didn\u2019t know\u2026"}, "geometry": {"type": "Point", "coordinates": [-119.61752319335938, 37.25510025024414]}}, {"type": "Feature", "id": 93, "properties": {"tag": "MeToo", "text": "RT @snowball1926: Here We go...True, not true?  Who are the @TheDemocrats going to believe.  What about the #MeToo movement?\n\n\"I was sexual\u2026"}, "geometry": {"type": "Point", "coordinates": [-99.3330307006836, 31.46275520324707]}}, {"type": "Feature", "id": 94, "properties": {"tag": "MeToo", "text": "RT @PrisonPlanet: Presidential candidate Mayor Pete Buttigieg is facing a potential #MeToo scandal after a Michigan man accused Buttigieg o\u2026"}, "geometry": {"type": "Point", "coordinates": [-98.98998260498047, 39.495914459228516]}}, {"type": "Feature", "id": 95, "properties": {"tag": "MeToo", "text": "@Maria_Memon @itsmeeshashafi Hahaha. This PTM and Metoo are tge new kewl to support"}, "geometry": {"type": "Point", "coordinates": [67.03437042236328, 24.92671012878418]}}, {"type": "Feature", "id": 96, "properties": {"tag": "MeToo", "text": "RT @EmHarriss: Whenever I hear men say, \u201cever since the #metoo era, we men have to be so careful\u201d .... I\u2019m like, be careful of what? Not ha\u2026"}, "geometry": {"type": "Point", "coordinates": [-2.4750399589538574, 52.7036018371582]}}, {"type": "Feature", "id": 97, "properties": {"tag": "MeToo", "text": "RT @ChatByCC: @Rockprincess818 \u201cMy name is Hunter Kelly. I am 21 years old. I was sexually assaulted by Mayor Pete Buttigieg. I didn\u2019t know\u2026"}, "geometry": {"type": "Point", "coordinates": [-79.18537902832031, 35.53935241699219]}}, {"type": "Feature", "id": 98, "properties": {"tag": "MeToo", "text": "RT @HtownDood: What do you make of this?\n#metoo?\nhttps://t.co/70LpXjeYvI"}, "geometry": {"type": "Point", "coordinates": [-99.3330307006836, 31.46275520324707]}}, {"type": "Feature", "id": 99, "properties": {"tag": "MeToo", "text": "Why women should have equal opportunities and rights in all countries worldwide: https://t.co/9dwQZEKSUv\n#feminism\u2026 https://t.co/FETc3z6GLk"}, "geometry": {"type": "Point", "coordinates": [26.282997131347656, 64.51988983154297]}}, {"type": "Feature", "id": 100, "properties": {"tag": "MeToo", "text": "\u2018MeToo\u2019 Hysteria: Handshakes In The Workplace Could Be Next On Chopping Block https://t.co/u7uvaWswxf"}, "geometry": {"type": "Point", "coordinates": [-119.61752319335938, 37.25510025024414]}}, {"type": "Feature", "id": 101, "properties": {"tag": "MeToo", "text": "RT @ChatByCC: @Rockprincess818 \u201cMy name is Hunter Kelly. I am 21 years old. I was sexually assaulted by Mayor Pete Buttigieg. I didn\u2019t know\u2026"}, "geometry": {"type": "Point", "coordinates": [-82.40010833740234, 34.848270416259766]}}, {"type": "Feature", "id": 102, "properties": {"tag": "MeToo", "text": "She says I'll check those msgs again ,wow chutyaa smjhaa hua hai awaam ko \nShe is fake Ali Zafar showed us proof wh\u2026 https://t.co/CWQer36z8m"}, "geometry": {"type": "Point", "coordinates": [68.80183410644531, 29.354202270507812]}}, {"type": "Feature", "id": 103, "properties": {"tag": "MeToo", "text": "RT @wkamaubell: The conversation w/ @emilyjoypoetry and her story of being abused in a megachurch that led her to create #ChurchToo (which\u2026"}, "geometry": {"type": "Point", "coordinates": [-83.53626251220703, 41.65380859375]}}, {"type": "Feature", "id": 104, "properties": {"tag": "MeToo", "text": "RT @nighatdad: I categorically deny the false and baseless allegations made against me by Ali Zafar on different TV shows regarding fake ac\u2026"}, "geometry": {"type": "Point", "coordinates": [73.07047271728516, 33.707679748535156]}}, {"type": "Feature", "id": 105, "properties": {"tag": "MeToo", "text": "#Metoo #Metooindia\nO' God save innocent men from fake molestation allegations... Save my country from fake accusers\u2026 https://t.co/hwNtX7xmjl"}, "geometry": {"type": "Point", "coordinates": [79.72701263427734, 22.493118286132812]}}, {"type": "Feature", "id": 106, "properties": {"tag": "MeToo", "text": "We need more journalists like @shazbkhanzdaGEO who knows exactly how to conduct an interview based on a very sensit\u2026 https://t.co/7J7NuNWWnj"}, "geometry": {"type": "Point", "coordinates": [73.07047271728516, 33.707679748535156]}}, {"type": "Feature", "id": 107, "properties": {"tag": "MeToo", "text": "#nonprofits need to be at the forefront of the #metoo movement. Learn how to address the pervasive issue of sexual\u2026 https://t.co/A8MucgQ9S2"}, "geometry": {"type": "Point", "coordinates": [-97.74298858642578, 30.267589569091797]}}, {"type": "Feature", "id": 108, "properties": {"tag": "MeToo", "text": "RT @ChatByCC: @Rockprincess818 \u201cMy name is Hunter Kelly. I am 21 years old. I was sexually assaulted by Mayor Pete Buttigieg. I didn\u2019t know\u2026"}, "geometry": {"type": "Point", "coordinates": [-122.41963958740234, 37.77711868286133]}}, {"type": "Feature", "id": 109, "properties": {"tag": "MeToo", "text": "RT @PrisonPlanet: Presidential candidate Mayor Pete Buttigieg is facing a potential #MeToo scandal after a Michigan man accused Buttigieg o\u2026"}, "geometry": {"type": "Point", "coordinates": [-77.83875274658203, 40.89651107788086]}}, {"type": "Feature", "id": 110, "properties": {"tag": "MeToo", "text": "RT @RealRCMaxwell: It's truly disgusting how Democrats are using #metoo to tear down American scholar and Black icon Clarence Thomas.\nhttps\u2026"}, "geometry": {"type": "Point", "coordinates": [-114.46959686279297, 42.556190490722656]}}, {"type": "Feature", "id": 111, "properties": {"tag": "MeToo", "text": "Pelosi stands by Gropey Joe Biden\n\nSays accusations against Biden DO NOT disqualify him from being President\n\nSo mu\u2026 https://t.co/nDmws7ZyvL"}, "geometry": {"type": "Point", "coordinates": [-98.98998260498047, 39.495914459228516]}}, {"type": "Feature", "id": 112, "properties": {"tag": "MeToo", "text": "RT @ChatByCC: \u201cMy name is Hunter Kelly. I am 21 years old. I was sexually assaulted by Mayor Pete Buttigieg. I didn\u2019t know who he was back\u2026"}, "geometry": {"type": "Point", "coordinates": [-86.28179931640625, 39.919803619384766]}}, {"type": "Feature", "id": 113, "properties": {"tag": "MeToo", "text": "RT @j_gelling: @ChatByCC @Rockprincess818 I'm not joining #MeToo but as with all these allegations we need to hear from the victim and the\u2026"}, "geometry": {"type": "Point", "coordinates": [-77.83875274658203, 40.89651107788086]}}, {"type": "Feature", "id": 114, "properties": {"tag": "MeToo", "text": "@hunterkelly  Thank you for your testimony of  a horrible experience.  \n#Buttigieg  is a non-starter and you just p\u2026 https://t.co/PrTL6n7rRb"}, "geometry": {"type": "Point", "coordinates": [-92.4778823852539, 38.36796569824219]}}, {"type": "Feature", "id": 115, "properties": {"tag": "MeToo", "text": "RT @FaerieWhings: A #MeToo story in the works.\n\nI hope Hunter heals. \n\nhttps://t.co/reIkzxTvt6"}, "geometry": {"type": "Point", "coordinates": [-84.39111328125, 33.74831008911133]}}, {"type": "Feature", "id": 116, "properties": {"tag": "MeToo", "text": "RT @OGMurphy1: I AM ASHAMED BY BREXIT..\n\nThe way migrants were used as a scapegoat for our own government's economic failure;\n\nThe way chea\u2026"}, "geometry": {"type": "Point", "coordinates": [9.181779861450195, 45.467960357666016]}}, {"type": "Feature", "id": 117, "properties": {"tag": "MeToo", "text": "RT @ChatByCC: @Rockprincess818 \u201cMy name is Hunter Kelly. I am 21 years old. I was sexually assaulted by Mayor Pete Buttigieg. I didn\u2019t know\u2026"}, "geometry": {"type": "Point", "coordinates": [-84.39111328125, 33.74831008911133]}}, {"type": "Feature", "id": 118, "properties": {"tag": "MeToo", "text": "I\u2019m curious if @GeorgeTakei will be as hard on #PeteButtigieg as he was on Brett Kavanaugh. #metoo right Sulu?? \u201cal\u2026 https://t.co/5wwqW49mQn"}, "geometry": {"type": "Point", "coordinates": [-82.47222137451172, 28.49258041381836]}}, {"type": "Feature", "id": 119, "properties": {"tag": "MeToo", "text": "RT @PrisonPlanet: Presidential candidate Mayor Pete Buttigieg is facing a potential #MeToo scandal after a Michigan man accused Buttigieg o\u2026"}, "geometry": {"type": "Point", "coordinates": [-0.12721000611782074, 51.50642013549805]}}, {"type": "Feature", "id": 120, "properties": {"tag": "MeToo", "text": "When you see someone in a bar being creepy to guests or staff, the worst thing you can do Is nothing -- by bartende\u2026 https://t.co/PledO0zWBd"}, "geometry": {"type": "Point", "coordinates": [-78.64266967773438, 35.7855110168457]}}, {"type": "Feature", "id": 121, "properties": {"tag": "MeToo", "text": "RT @morethanmySLE: If it wasn't for the bravery of @TaranaBurke &amp; @Alyssa_Milano I would have NEVER shared my #metoo story.\n\nListening to @\u2026"}, "geometry": {"type": "Point", "coordinates": [-73.96624755859375, 40.7834358215332]}}, {"type": "Feature", "id": 122, "properties": {"tag": "MeToo", "text": "RT @morethanmySLE: \u201cIt\u2019s very healing to share your story, &amp; the only way that we can prevent this from happening, is to talk about it, &amp; k\u2026"}, "geometry": {"type": "Point", "coordinates": [-73.96624755859375, 40.7834358215332]}}, {"type": "Feature", "id": 123, "properties": {"tag": "MeToo", "text": "RT @RichGas8: @TBInvestigation Another crazy ass liberal....every mass shooting since President Trump was elected has been a liberal. Every\u2026"}, "geometry": {"type": "Point", "coordinates": [-80.2874984741211, 40.86030197143555]}}, {"type": "Feature", "id": 124, "properties": {"tag": "MeToo", "text": "Little Did I Know by Songbird inspired by #MichealJackson and #MeToo Sherri\u2019s #lies https://t.co/kfxfs75psl for\u2026 https://t.co/HbNKyWfrNX"}, "geometry": {"type": "Point", "coordinates": [-79.38543701171875, 43.64868927001953]}}, {"type": "Feature", "id": 125, "properties": {"tag": "MeToo", "text": "RT @morethanmySLE: If it wasn't for the bravery of @TaranaBurke &amp; @Alyssa_Milano I would have NEVER shared my #metoo story.\n\nListening to @\u2026"}, "geometry": {"type": "Point", "coordinates": [-119.61752319335938, 37.25510025024414]}}, {"type": "Feature", "id": 126, "properties": {"tag": "MeToo", "text": "RT @ScottRickhoff: Democrat Nobody Pete #Buttplug Accused of Sexual Assault by 21-Year-Old from Michigan. #Metoo #WalkAwayFromDemocrats #Wa\u2026"}, "geometry": {"type": "Point", "coordinates": [-92.8105697631836, 45.05670166015625]}}, {"type": "Feature", "id": 127, "properties": {"tag": "MeToo", "text": "Interesting that of your handful of likes, all but one are super supportive of Bernie and you have a whopping 1 act\u2026 https://t.co/kuXzwtnEBg"}, "geometry": {"type": "Point", "coordinates": [-89.64360046386719, 39.801048278808594]}}, {"type": "Feature", "id": 128, "properties": {"tag": "MeToo", "text": "Democrats allowed #MeToo to run untethered and unchecked when it benefited them. Anyone wanna place bets on how qui\u2026 https://t.co/0qE5IrmZMc"}, "geometry": {"type": "Point", "coordinates": [-91.1167984008789, 48.04707717895508]}}, {"type": "Feature", "id": 129, "properties": {"tag": "MeToo", "text": "RT @ScottRickhoff: Democrat Nobody Pete #Buttplug Accused of Sexual Assault by 21-Year-Old from Michigan. #Metoo #WalkAwayFromDemocrats #Wa\u2026"}, "geometry": {"type": "Point", "coordinates": [-83.4445571899414, 32.64833068847656]}}, {"type": "Feature", "id": 130, "properties": {"tag": "MeToo", "text": "RT @TheAbdullahKhan: First of all I think Shahzeb Khanzada deserves credit for conducting a highly professional interview with Meesha Shafi\u2026"}, "geometry": {"type": "Point", "coordinates": [73.07047271728516, 33.707679748535156]}}, {"type": "Feature", "id": 131, "properties": {"tag": "MeToo", "text": "RT @FullStopFdn: \"The underlying driver of sexual harassment in workplaces is power and the misuse of power, and because different workplac\u2026"}, "geometry": {"type": "Point", "coordinates": [144.53526306152344, -22.575700759887695]}}, {"type": "Feature", "id": 132, "properties": {"tag": "MeToo", "text": "@SuperPatriotone Wow, the #MeToo movement should be all over this.\n\nWhere is @Alyssa_Milano on this and did she ask\u2026 https://t.co/3FHTRnFdpd"}, "geometry": {"type": "Point", "coordinates": [-86.34304809570312, 35.84300231933594]}}, {"type": "Feature", "id": 133, "properties": {"tag": "MeToo", "text": "RT @FaerieWhings: A #MeToo story in the works.\n\nI hope Hunter heals. \n\nhttps://t.co/reIkzxTvt6"}, "geometry": {"type": "Point", "coordinates": [-118.472325, 34.2276600003532]}}, {"type": "Feature", "id": 134, "properties": {"tag": "MeToo", "text": "@darklordjournal @AspcraAdInferi Nah, not really. #MeToo"}, "geometry": {"type": "Point", "coordinates": [-150.05264282226562, 62.206478118896484]}}, {"type": "Feature", "id": 135, "properties": {"tag": "MeToo", "text": "Mayor Pete Hit With #MeToo Allegation of Sexual Assault https://t.co/M0tWnxJ9hw"}, "geometry": {"type": "Point", "coordinates": [-85.2876205444336, 37.5272331237793]}}, {"type": "Feature", "id": 136, "properties": {"tag": "MeToo", "text": "Democrat Nobody Pete #Buttplug Accused of Sexual Assault by 21-Year-Old from Michigan. #Metoo\u2026 https://t.co/SQ2K64c8tk"}, "geometry": {"type": "Point", "coordinates": [-98.98998260498047, 39.495914459228516]}}, {"type": "Feature", "id": 137, "properties": {"tag": "MeToo", "text": "RT @OGMurphy1: I AM ASHAMED BY BREXIT..\n\nThe way migrants were used as a scapegoat for our own government's economic failure;\n\nThe way chea\u2026"}, "geometry": {"type": "Point", "coordinates": [-2.5505640506744385, 53.9438362121582]}}, {"type": "Feature", "id": 138, "properties": {"tag": "MeToo", "text": "RT @ChatByCC: \u201cMy name is Hunter Kelly. I am 21 years old. I was sexually assaulted by Mayor Pete Buttigieg. I didn\u2019t know who he was back\u2026"}, "geometry": {"type": "Point", "coordinates": [-77.83875274658203, 40.89651107788086]}}, {"type": "Feature", "id": 139, "properties": {"tag": "MeToo", "text": "@gatewaypundit #metoo  - time to treat ol Pete like Kavanaugh"}, "geometry": {"type": "Point", "coordinates": [-85.73513793945312, 44.86261749267578]}}, {"type": "Feature", "id": 140, "properties": {"tag": "MeToo", "text": "RT @FreedomForumIns: \u201cIn late 2017 when #MeToo revelations exposed sexual harassment &amp; misconduct in many media organizations, we immediate\u2026"}, "geometry": {"type": "Point", "coordinates": [-89.73674011230469, 44.64178466796875]}}, {"type": "Feature", "id": 141, "properties": {"tag": "MeToo", "text": "@NickANigro @worldincommon @thesweatytuna @MrFesser @StarTribune The Vikings were known as rapists and pillagers wh\u2026 https://t.co/MG3wnKA4e6"}, "geometry": {"type": "Point", "coordinates": [-94.19837188720703, 46.34935760498047]}}, {"type": "Feature", "id": 142, "properties": {"tag": "MeToo", "text": "@diamondsnjeans @RonHall46 At last! An opportunity for me to say:\n\n     MeToo"}, "geometry": {"type": "Point", "coordinates": [-0.12721000611782074, 51.50642013549805]}}, {"type": "Feature", "id": 143, "properties": {"tag": "MeToo", "text": "Why people speaking in favour of PTM and Meesha shafi are the same ? "}, "geometry": {"type": "Point", "coordinates": [74.30348205566406, 31.53944969177246]}}, {"type": "Feature", "id": 144, "properties": {"tag": "MeToo", "text": "RT @ChatByCC: @Rockprincess818 \u201cMy name is Hunter Kelly. I am 21 years old. I was sexually assaulted by Mayor Pete Buttigieg. I didn\u2019t know\u2026"}, "geometry": {"type": "Point", "coordinates": [-119.61752319335938, 37.25510025024414]}}, {"type": "Feature", "id": 145, "properties": {"tag": "MeToo", "text": "RT @snowball1926: Here We go...True, not true?  Who are the @TheDemocrats going to believe.  What about the #MeToo movement?\n\n\"I was sexual\u2026"}, "geometry": {"type": "Point", "coordinates": [-99.3330307006836, 31.46275520324707]}}, {"type": "Feature", "id": 146, "properties": {"tag": "MeToo", "text": "RT @PrisonPlanet: Presidential candidate Mayor Pete Buttigieg is facing a potential #MeToo scandal after a Michigan man accused Buttigieg o\u2026"}, "geometry": {"type": "Point", "coordinates": [-98.98998260498047, 39.495914459228516]}}, {"type": "Feature", "id": 147, "properties": {"tag": "MeToo", "text": "@Maria_Memon @itsmeeshashafi Hahaha. This PTM and Metoo are tge new kewl to support"}, "geometry": {"type": "Point", "coordinates": [67.03437042236328, 24.92671012878418]}}, {"type": "Feature", "id": 148, "properties": {"tag": "MeToo", "text": "RT @EmHarriss: Whenever I hear men say, \u201cever since the #metoo era, we men have to be so careful\u201d .... I\u2019m like, be careful of what? Not ha\u2026"}, "geometry": {"type": "Point", "coordinates": [-2.4750399589538574, 52.7036018371582]}}, {"type": "Feature", "id": 149, "properties": {"tag": "MeToo", "text": "RT @ChatByCC: @Rockprincess818 \u201cMy name is Hunter Kelly. I am 21 years old. I was sexually assaulted by Mayor Pete Buttigieg. I didn\u2019t know\u2026"}, "geometry": {"type": "Point", "coordinates": [-79.18537902832031, 35.53935241699219]}}, {"type": "Feature", "id": 150, "properties": {"tag": "MeToo", "text": "RT @HtownDood: What do you make of this?\n#metoo?\nhttps://t.co/70LpXjeYvI"}, "geometry": {"type": "Point", "coordinates": [-99.3330307006836, 31.46275520324707]}}, {"type": "Feature", "id": 151, "properties": {"tag": "MeToo", "text": "Why women should have equal opportunities and rights in all countries worldwide: https://t.co/9dwQZEKSUv\n#feminism\u2026 https://t.co/FETc3z6GLk"}, "geometry": {"type": "Point", "coordinates": [26.282997131347656, 64.51988983154297]}}, {"type": "Feature", "id": 152, "properties": {"tag": "MeToo", "text": "\u2018MeToo\u2019 Hysteria: Handshakes In The Workplace Could Be Next On Chopping Block https://t.co/u7uvaWswxf"}, "geometry": {"type": "Point", "coordinates": [-119.61752319335938, 37.25510025024414]}}, {"type": "Feature", "id": 153, "properties": {"tag": "MeToo", "text": "RT @ChatByCC: @Rockprincess818 \u201cMy name is Hunter Kelly. I am 21 years old. I was sexually assaulted by Mayor Pete Buttigieg. I didn\u2019t know\u2026"}, "geometry": {"type": "Point", "coordinates": [-82.40010833740234, 34.848270416259766]}}, {"type": "Feature", "id": 154, "properties": {"tag": "MeToo", "text": "She says I'll check those msgs again ,wow chutyaa smjhaa hua hai awaam ko \nShe is fake Ali Zafar showed us proof wh\u2026 https://t.co/CWQer36z8m"}, "geometry": {"type": "Point", "coordinates": [68.80183410644531, 29.354202270507812]}}, {"type": "Feature", "id": 155, "properties": {"tag": "MeToo", "text": "RT @wkamaubell: The conversation w/ @emilyjoypoetry and her story of being abused in a megachurch that led her to create #ChurchToo (which\u2026"}, "geometry": {"type": "Point", "coordinates": [-83.53626251220703, 41.65380859375]}}, {"type": "Feature", "id": 156, "properties": {"tag": "MeToo", "text": "RT @nighatdad: I categorically deny the false and baseless allegations made against me by Ali Zafar on different TV shows regarding fake ac\u2026"}, "geometry": {"type": "Point", "coordinates": [73.07047271728516, 33.707679748535156]}}, {"type": "Feature", "id": 157, "properties": {"tag": "MeToo", "text": "#Metoo #Metooindia\nO' God save innocent men from fake molestation allegations... Save my country from fake accusers\u2026 https://t.co/hwNtX7xmjl"}, "geometry": {"type": "Point", "coordinates": [79.72701263427734, 22.493118286132812]}}, {"type": "Feature", "id": 158, "properties": {"tag": "MeToo", "text": "We need more journalists like @shazbkhanzdaGEO who knows exactly how to conduct an interview based on a very sensit\u2026 https://t.co/7J7NuNWWnj"}, "geometry": {"type": "Point", "coordinates": [73.07047271728516, 33.707679748535156]}}, {"type": "Feature", "id": 159, "properties": {"tag": "MeToo", "text": "#nonprofits need to be at the forefront of the #metoo movement. Learn how to address the pervasive issue of sexual\u2026 https://t.co/A8MucgQ9S2"}, "geometry": {"type": "Point", "coordinates": [-97.74298858642578, 30.267589569091797]}}, {"type": "Feature", "id": 160, "properties": {"tag": "MeToo", "text": "RT @ChatByCC: @Rockprincess818 \u201cMy name is Hunter Kelly. I am 21 years old. I was sexually assaulted by Mayor Pete Buttigieg. I didn\u2019t know\u2026"}, "geometry": {"type": "Point", "coordinates": [-122.41963958740234, 37.77711868286133]}}, {"type": "Feature", "id": 161, "properties": {"tag": "MeToo", "text": "RT @PrisonPlanet: Presidential candidate Mayor Pete Buttigieg is facing a potential #MeToo scandal after a Michigan man accused Buttigieg o\u2026"}, "geometry": {"type": "Point", "coordinates": [-77.83875274658203, 40.89651107788086]}}, {"type": "Feature", "id": 162, "properties": {"tag": "MeToo", "text": "RT @RealRCMaxwell: It's truly disgusting how Democrats are using #metoo to tear down American scholar and Black icon Clarence Thomas.\nhttps\u2026"}, "geometry": {"type": "Point", "coordinates": [-114.46959686279297, 42.556190490722656]}}, {"type": "Feature", "id": 163, "properties": {"tag": "MeToo", "text": "Pelosi stands by Gropey Joe Biden\n\nSays accusations against Biden DO NOT disqualify him from being President\n\nSo mu\u2026 https://t.co/nDmws7ZyvL"}, "geometry": {"type": "Point", "coordinates": [-98.98998260498047, 39.495914459228516]}}, {"type": "Feature", "id": 164, "properties": {"tag": "MeToo", "text": "RT @ChatByCC: \u201cMy name is Hunter Kelly. I am 21 years old. I was sexually assaulted by Mayor Pete Buttigieg. I didn\u2019t know who he was back\u2026"}, "geometry": {"type": "Point", "coordinates": [-86.28179931640625, 39.919803619384766]}}, {"type": "Feature", "id": 165, "properties": {"tag": "MeToo", "text": "RT @j_gelling: @ChatByCC @Rockprincess818 I'm not joining #MeToo but as with all these allegations we need to hear from the victim and the\u2026"}, "geometry": {"type": "Point", "coordinates": [-77.83875274658203, 40.89651107788086]}}, {"type": "Feature", "id": 166, "properties": {"tag": "MeToo", "text": "@hunterkelly  Thank you for your testimony of  a horrible experience.  \n#Buttigieg  is a non-starter and you just p\u2026 https://t.co/PrTL6n7rRb"}, "geometry": {"type": "Point", "coordinates": [-92.4778823852539, 38.36796569824219]}}, {"type": "Feature", "id": 167, "properties": {"tag": "MeToo", "text": "RT @FaerieWhings: A #MeToo story in the works.\n\nI hope Hunter heals. \n\nhttps://t.co/reIkzxTvt6"}, "geometry": {"type": "Point", "coordinates": [-84.39111328125, 33.74831008911133]}}, {"type": "Feature", "id": 168, "properties": {"tag": "MeToo", "text": "RT @OGMurphy1: I AM ASHAMED BY BREXIT..\n\nThe way migrants were used as a scapegoat for our own government's economic failure;\n\nThe way chea\u2026"}, "geometry": {"type": "Point", "coordinates": [9.181779861450195, 45.467960357666016]}}, {"type": "Feature", "id": 169, "properties": {"tag": "MeToo", "text": "RT @ChatByCC: @Rockprincess818 \u201cMy name is Hunter Kelly. I am 21 years old. I was sexually assaulted by Mayor Pete Buttigieg. I didn\u2019t know\u2026"}, "geometry": {"type": "Point", "coordinates": [-84.39111328125, 33.74831008911133]}}, {"type": "Feature", "id": 170, "properties": {"tag": "MeToo", "text": "I\u2019m curious if @GeorgeTakei will be as hard on #PeteButtigieg as he was on Brett Kavanaugh. #metoo right Sulu?? \u201cal\u2026 https://t.co/5wwqW49mQn"}, "geometry": {"type": "Point", "coordinates": [-82.47222137451172, 28.49258041381836]}}, {"type": "Feature", "id": 171, "properties": {"tag": "MeToo", "text": "RT @PrisonPlanet: Presidential candidate Mayor Pete Buttigieg is facing a potential #MeToo scandal after a Michigan man accused Buttigieg o\u2026"}, "geometry": {"type": "Point", "coordinates": [-0.12721000611782074, 51.50642013549805]}}, {"type": "Feature", "id": 172, "properties": {"tag": "MeToo", "text": "When you see someone in a bar being creepy to guests or staff, the worst thing you can do Is nothing -- by bartende\u2026 https://t.co/PledO0zWBd"}, "geometry": {"type": "Point", "coordinates": [-78.64266967773438, 35.7855110168457]}}, {"type": "Feature", "id": 173, "properties": {"tag": "MeToo", "text": "RT @morethanmySLE: If it wasn't for the bravery of @TaranaBurke &amp; @Alyssa_Milano I would have NEVER shared my #metoo story.\n\nListening to @\u2026"}, "geometry": {"type": "Point", "coordinates": [-73.96624755859375, 40.7834358215332]}}, {"type": "Feature", "id": 174, "properties": {"tag": "MeToo", "text": "RT @morethanmySLE: \u201cIt\u2019s very healing to share your story, &amp; the only way that we can prevent this from happening, is to talk about it, &amp; k\u2026"}, "geometry": {"type": "Point", "coordinates": [-73.96624755859375, 40.7834358215332]}}, {"type": "Feature", "id": 175, "properties": {"tag": "MeToo", "text": "RT @RichGas8: @TBInvestigation Another crazy ass liberal....every mass shooting since President Trump was elected has been a liberal. Every\u2026"}, "geometry": {"type": "Point", "coordinates": [-80.2874984741211, 40.86030197143555]}}, {"type": "Feature", "id": 176, "properties": {"tag": "MeToo", "text": "Little Did I Know by Songbird inspired by #MichealJackson and #MeToo Sherri\u2019s #lies https://t.co/kfxfs75psl for\u2026 https://t.co/HbNKyWfrNX"}, "geometry": {"type": "Point", "coordinates": [-79.38543701171875, 43.64868927001953]}}, {"type": "Feature", "id": 177, "properties": {"tag": "MeToo", "text": "RT @morethanmySLE: If it wasn't for the bravery of @TaranaBurke &amp; @Alyssa_Milano I would have NEVER shared my #metoo story.\n\nListening to @\u2026"}, "geometry": {"type": "Point", "coordinates": [-119.61752319335938, 37.25510025024414]}}, {"type": "Feature", "id": 178, "properties": {"tag": "MeToo", "text": "RT @ScottRickhoff: Democrat Nobody Pete #Buttplug Accused of Sexual Assault by 21-Year-Old from Michigan. #Metoo #WalkAwayFromDemocrats #Wa\u2026"}, "geometry": {"type": "Point", "coordinates": [-92.8105697631836, 45.05670166015625]}}, {"type": "Feature", "id": 179, "properties": {"tag": "MeToo", "text": "Interesting that of your handful of likes, all but one are super supportive of Bernie and you have a whopping 1 act\u2026 https://t.co/kuXzwtnEBg"}, "geometry": {"type": "Point", "coordinates": [-89.64360046386719, 39.801048278808594]}}, {"type": "Feature", "id": 180, "properties": {"tag": "MeToo", "text": "Democrats allowed #MeToo to run untethered and unchecked when it benefited them. Anyone wanna place bets on how qui\u2026 https://t.co/0qE5IrmZMc"}, "geometry": {"type": "Point", "coordinates": [-91.1167984008789, 48.04707717895508]}}, {"type": "Feature", "id": 181, "properties": {"tag": "MeToo", "text": "RT @ScottRickhoff: Democrat Nobody Pete #Buttplug Accused of Sexual Assault by 21-Year-Old from Michigan. #Metoo #WalkAwayFromDemocrats #Wa\u2026"}, "geometry": {"type": "Point", "coordinates": [-83.4445571899414, 32.64833068847656]}}, {"type": "Feature", "id": 182, "properties": {"tag": "MeToo", "text": "RT @TheAbdullahKhan: First of all I think Shahzeb Khanzada deserves credit for conducting a highly professional interview with Meesha Shafi\u2026"}, "geometry": {"type": "Point", "coordinates": [73.07047271728516, 33.707679748535156]}}, {"type": "Feature", "id": 183, "properties": {"tag": "MeToo", "text": "RT @FullStopFdn: \"The underlying driver of sexual harassment in workplaces is power and the misuse of power, and because different workplac\u2026"}, "geometry": {"type": "Point", "coordinates": [144.53526306152344, -22.575700759887695]}}, {"type": "Feature", "id": 184, "properties": {"tag": "MeToo", "text": "@SuperPatriotone Wow, the #MeToo movement should be all over this.\n\nWhere is @Alyssa_Milano on this and did she ask\u2026 https://t.co/3FHTRnFdpd"}, "geometry": {"type": "Point", "coordinates": [-86.34304809570312, 35.84300231933594]}}, {"type": "Feature", "id": 185, "properties": {"tag": "MeToo", "text": "RT @FaerieWhings: A #MeToo story in the works.\n\nI hope Hunter heals. \n\nhttps://t.co/reIkzxTvt6"}, "geometry": {"type": "Point", "coordinates": [-118.472325, 34.2276600003532]}}, {"type": "Feature", "id": 186, "properties": {"tag": "MeToo", "text": "@darklordjournal @AspcraAdInferi Nah, not really. #MeToo"}, "geometry": {"type": "Point", "coordinates": [-150.05264282226562, 62.206478118896484]}}, {"type": "Feature", "id": 187, "properties": {"tag": "MeToo", "text": "Mayor Pete Hit With #MeToo Allegation of Sexual Assault https://t.co/M0tWnxJ9hw"}, "geometry": {"type": "Point", "coordinates": [-85.2876205444336, 37.5272331237793]}}, {"type": "Feature", "id": 188, "properties": {"tag": "MeToo", "text": "Democrat Nobody Pete #Buttplug Accused of Sexual Assault by 21-Year-Old from Michigan. #Metoo\u2026 https://t.co/SQ2K64c8tk"}, "geometry": {"type": "Point", "coordinates": [-98.98998260498047, 39.495914459228516]}}, {"type": "Feature", "id": 189, "properties": {"tag": "MeToo", "text": "RT @OGMurphy1: I AM ASHAMED BY BREXIT..\n\nThe way migrants were used as a scapegoat for our own government's economic failure;\n\nThe way chea\u2026"}, "geometry": {"type": "Point", "coordinates": [-2.5505640506744385, 53.9438362121582]}}, {"type": "Feature", "id": 190, "properties": {"tag": "MeToo", "text": "RT @ChatByCC: \u201cMy name is Hunter Kelly. I am 21 years old. I was sexually assaulted by Mayor Pete Buttigieg. I didn\u2019t know who he was back\u2026"}, "geometry": {"type": "Point", "coordinates": [-77.83875274658203, 40.89651107788086]}}, {"type": "Feature", "id": 191, "properties": {"tag": "MeToo", "text": "@gatewaypundit #metoo  - time to treat ol Pete like Kavanaugh"}, "geometry": {"type": "Point", "coordinates": [-85.73513793945312, 44.86261749267578]}}, {"type": "Feature", "id": 192, "properties": {"tag": "MeToo", "text": "RT @FreedomForumIns: \u201cIn late 2017 when #MeToo revelations exposed sexual harassment &amp; misconduct in many media organizations, we immediate\u2026"}, "geometry": {"type": "Point", "coordinates": [-89.73674011230469, 44.64178466796875]}}, {"type": "Feature", "id": 193, "properties": {"tag": "MeToo", "text": "@NickANigro @worldincommon @thesweatytuna @MrFesser @StarTribune The Vikings were known as rapists and pillagers wh\u2026 https://t.co/MG3wnKA4e6"}, "geometry": {"type": "Point", "coordinates": [-94.19837188720703, 46.34935760498047]}}, {"type": "Feature", "id": 194, "properties": {"tag": "MeToo", "text": "@diamondsnjeans @RonHall46 At last! An opportunity for me to say:\n\n     MeToo"}, "geometry": {"type": "Point", "coordinates": [-0.12721000611782074, 51.50642013549805]}}, {"type": "Feature", "id": 195, "properties": {"tag": "MeToo", "text": "Why people speaking in favour of PTM and Meesha shafi are the same ? "}, "geometry": {"type": "Point", "coordinates": [74.30348205566406, 31.53944969177246]}}, {"type": "Feature", "id": 196, "properties": {"tag": "MeToo", "text": "RT @ChatByCC: @Rockprincess818 \u201cMy name is Hunter Kelly. I am 21 years old. I was sexually assaulted by Mayor Pete Buttigieg. I didn\u2019t know\u2026"}, "geometry": {"type": "Point", "coordinates": [-119.61752319335938, 37.25510025024414]}}, {"type": "Feature", "id": 197, "properties": {"tag": "MeToo", "text": "RT @snowball1926: Here We go...True, not true?  Who are the @TheDemocrats going to believe.  What about the #MeToo movement?\n\n\"I was sexual\u2026"}, "geometry": {"type": "Point", "coordinates": [-99.3330307006836, 31.46275520324707]}}, {"type": "Feature", "id": 198, "properties": {"tag": "MeToo", "text": "RT @PrisonPlanet: Presidential candidate Mayor Pete Buttigieg is facing a potential #MeToo scandal after a Michigan man accused Buttigieg o\u2026"}, "geometry": {"type": "Point", "coordinates": [-98.98998260498047, 39.495914459228516]}}, {"type": "Feature", "id": 199, "properties": {"tag": "MeToo", "text": "@Maria_Memon @itsmeeshashafi Hahaha. This PTM and Metoo are tge new kewl to support"}, "geometry": {"type": "Point", "coordinates": [67.03437042236328, 24.92671012878418]}}, {"type": "Feature", "id": 200, "properties": {"tag": "MeToo", "text": "RT @EmHarriss: Whenever I hear men say, \u201cever since the #metoo era, we men have to be so careful\u201d .... I\u2019m like, be careful of what? Not ha\u2026"}, "geometry": {"type": "Point", "coordinates": [-2.4750399589538574, 52.7036018371582]}}, {"type": "Feature", "id": 201, "properties": {"tag": "MeToo", "text": "RT @ChatByCC: @Rockprincess818 \u201cMy name is Hunter Kelly. I am 21 years old. I was sexually assaulted by Mayor Pete Buttigieg. I didn\u2019t know\u2026"}, "geometry": {"type": "Point", "coordinates": [-79.18537902832031, 35.53935241699219]}}, {"type": "Feature", "id": 202, "properties": {"tag": "MeToo", "text": "RT @HtownDood: What do you make of this?\n#metoo?\nhttps://t.co/70LpXjeYvI"}, "geometry": {"type": "Point", "coordinates": [-99.3330307006836, 31.46275520324707]}}, {"type": "Feature", "id": 203, "properties": {"tag": "MeToo", "text": "Why women should have equal opportunities and rights in all countries worldwide: https://t.co/9dwQZEKSUv\n#feminism\u2026 https://t.co/FETc3z6GLk"}, "geometry": {"type": "Point", "coordinates": [26.282997131347656, 64.51988983154297]}}, {"type": "Feature", "id": 204, "properties": {"tag": "MeToo", "text": "\u2018MeToo\u2019 Hysteria: Handshakes In The Workplace Could Be Next On Chopping Block https://t.co/u7uvaWswxf"}, "geometry": {"type": "Point", "coordinates": [-119.61752319335938, 37.25510025024414]}}, {"type": "Feature", "id": 205, "properties": {"tag": "MeToo", "text": "RT @ChatByCC: @Rockprincess818 \u201cMy name is Hunter Kelly. I am 21 years old. I was sexually assaulted by Mayor Pete Buttigieg. I didn\u2019t know\u2026"}, "geometry": {"type": "Point", "coordinates": [-82.40010833740234, 34.848270416259766]}}, {"type": "Feature", "id": 206, "properties": {"tag": "MeToo", "text": "She says I'll check those msgs again ,wow chutyaa smjhaa hua hai awaam ko \nShe is fake Ali Zafar showed us proof wh\u2026 https://t.co/CWQer36z8m"}, "geometry": {"type": "Point", "coordinates": [68.80183410644531, 29.354202270507812]}}, {"type": "Feature", "id": 207, "properties": {"tag": "MeToo", "text": "RT @wkamaubell: The conversation w/ @emilyjoypoetry and her story of being abused in a megachurch that led her to create #ChurchToo (which\u2026"}, "geometry": {"type": "Point", "coordinates": [-83.53626251220703, 41.65380859375]}}, {"type": "Feature", "id": 208, "properties": {"tag": "MeToo", "text": "RT @nighatdad: I categorically deny the false and baseless allegations made against me by Ali Zafar on different TV shows regarding fake ac\u2026"}, "geometry": {"type": "Point", "coordinates": [73.07047271728516, 33.707679748535156]}}, {"type": "Feature", "id": 209, "properties": {"tag": "MeToo", "text": "#Metoo #Metooindia\nO' God save innocent men from fake molestation allegations... Save my country from fake accusers\u2026 https://t.co/hwNtX7xmjl"}, "geometry": {"type": "Point", "coordinates": [79.72701263427734, 22.493118286132812]}}, {"type": "Feature", "id": 210, "properties": {"tag": "MeToo", "text": "We need more journalists like @shazbkhanzdaGEO who knows exactly how to conduct an interview based on a very sensit\u2026 https://t.co/7J7NuNWWnj"}, "geometry": {"type": "Point", "coordinates": [73.07047271728516, 33.707679748535156]}}, {"type": "Feature", "id": 211, "properties": {"tag": "MeToo", "text": "#nonprofits need to be at the forefront of the #metoo movement. Learn how to address the pervasive issue of sexual\u2026 https://t.co/A8MucgQ9S2"}, "geometry": {"type": "Point", "coordinates": [-97.74298858642578, 30.267589569091797]}}, {"type": "Feature", "id": 212, "properties": {"tag": "MeToo", "text": "RT @ChatByCC: @Rockprincess818 \u201cMy name is Hunter Kelly. I am 21 years old. I was sexually assaulted by Mayor Pete Buttigieg. I didn\u2019t know\u2026"}, "geometry": {"type": "Point", "coordinates": [-122.41963958740234, 37.77711868286133]}}, {"type": "Feature", "id": 213, "properties": {"tag": "MeToo", "text": "RT @PrisonPlanet: Presidential candidate Mayor Pete Buttigieg is facing a potential #MeToo scandal after a Michigan man accused Buttigieg o\u2026"}, "geometry": {"type": "Point", "coordinates": [-77.83875274658203, 40.89651107788086]}}, {"type": "Feature", "id": 214, "properties": {"tag": "MeToo", "text": "RT @RealRCMaxwell: It's truly disgusting how Democrats are using #metoo to tear down American scholar and Black icon Clarence Thomas.\nhttps\u2026"}, "geometry": {"type": "Point", "coordinates": [-114.46959686279297, 42.556190490722656]}}, {"type": "Feature", "id": 215, "properties": {"tag": "MeToo", "text": "Pelosi stands by Gropey Joe Biden\n\nSays accusations against Biden DO NOT disqualify him from being President\n\nSo mu\u2026 https://t.co/nDmws7ZyvL"}, "geometry": {"type": "Point", "coordinates": [-98.98998260498047, 39.495914459228516]}}, {"type": "Feature", "id": 216, "properties": {"tag": "MeToo", "text": "RT @ChatByCC: \u201cMy name is Hunter Kelly. I am 21 years old. I was sexually assaulted by Mayor Pete Buttigieg. I didn\u2019t know who he was back\u2026"}, "geometry": {"type": "Point", "coordinates": [-86.28179931640625, 39.919803619384766]}}, {"type": "Feature", "id": 217, "properties": {"tag": "MeToo", "text": "RT @j_gelling: @ChatByCC @Rockprincess818 I'm not joining #MeToo but as with all these allegations we need to hear from the victim and the\u2026"}, "geometry": {"type": "Point", "coordinates": [-77.83875274658203, 40.89651107788086]}}, {"type": "Feature", "id": 218, "properties": {"tag": "MeToo", "text": "@hunterkelly  Thank you for your testimony of  a horrible experience.  \n#Buttigieg  is a non-starter and you just p\u2026 https://t.co/PrTL6n7rRb"}, "geometry": {"type": "Point", "coordinates": [-92.4778823852539, 38.36796569824219]}}, {"type": "Feature", "id": 219, "properties": {"tag": "MeToo", "text": "RT @FaerieWhings: A #MeToo story in the works.\n\nI hope Hunter heals. \n\nhttps://t.co/reIkzxTvt6"}, "geometry": {"type": "Point", "coordinates": [-84.39111328125, 33.74831008911133]}}, {"type": "Feature", "id": 220, "properties": {"tag": "MeToo", "text": "RT @OGMurphy1: I AM ASHAMED BY BREXIT..\n\nThe way migrants were used as a scapegoat for our own government's economic failure;\n\nThe way chea\u2026"}, "geometry": {"type": "Point", "coordinates": [9.181779861450195, 45.467960357666016]}}, {"type": "Feature", "id": 221, "properties": {"tag": "MeToo", "text": "RT @ChatByCC: @Rockprincess818 \u201cMy name is Hunter Kelly. I am 21 years old. I was sexually assaulted by Mayor Pete Buttigieg. I didn\u2019t know\u2026"}, "geometry": {"type": "Point", "coordinates": [-84.39111328125, 33.74831008911133]}}, {"type": "Feature", "id": 222, "properties": {"tag": "MeToo", "text": "I\u2019m curious if @GeorgeTakei will be as hard on #PeteButtigieg as he was on Brett Kavanaugh. #metoo right Sulu?? \u201cal\u2026 https://t.co/5wwqW49mQn"}, "geometry": {"type": "Point", "coordinates": [-82.47222137451172, 28.49258041381836]}}, {"type": "Feature", "id": 223, "properties": {"tag": "MeToo", "text": "RT @PrisonPlanet: Presidential candidate Mayor Pete Buttigieg is facing a potential #MeToo scandal after a Michigan man accused Buttigieg o\u2026"}, "geometry": {"type": "Point", "coordinates": [-0.12721000611782074, 51.50642013549805]}}, {"type": "Feature", "id": 224, "properties": {"tag": "MeToo", "text": "When you see someone in a bar being creepy to guests or staff, the worst thing you can do Is nothing -- by bartende\u2026 https://t.co/PledO0zWBd"}, "geometry": {"type": "Point", "coordinates": [-78.64266967773438, 35.7855110168457]}}, {"type": "Feature", "id": 225, "properties": {"tag": "MeToo", "text": "RT @morethanmySLE: If it wasn't for the bravery of @TaranaBurke &amp; @Alyssa_Milano I would have NEVER shared my #metoo story.\n\nListening to @\u2026"}, "geometry": {"type": "Point", "coordinates": [-73.96624755859375, 40.7834358215332]}}, {"type": "Feature", "id": 226, "properties": {"tag": "MeToo", "text": "RT @morethanmySLE: \u201cIt\u2019s very healing to share your story, &amp; the only way that we can prevent this from happening, is to talk about it, &amp; k\u2026"}, "geometry": {"type": "Point", "coordinates": [-73.96624755859375, 40.7834358215332]}}, {"type": "Feature", "id": 227, "properties": {"tag": "MeToo", "text": "RT @RichGas8: @TBInvestigation Another crazy ass liberal....every mass shooting since President Trump was elected has been a liberal. Every\u2026"}, "geometry": {"type": "Point", "coordinates": [-80.2874984741211, 40.86030197143555]}}, {"type": "Feature", "id": 228, "properties": {"tag": "MeToo", "text": "Little Did I Know by Songbird inspired by #MichealJackson and #MeToo Sherri\u2019s #lies https://t.co/kfxfs75psl for\u2026 https://t.co/HbNKyWfrNX"}, "geometry": {"type": "Point", "coordinates": [-79.38543701171875, 43.64868927001953]}}, {"type": "Feature", "id": 229, "properties": {"tag": "MeToo", "text": "RT @morethanmySLE: If it wasn't for the bravery of @TaranaBurke &amp; @Alyssa_Milano I would have NEVER shared my #metoo story.\n\nListening to @\u2026"}, "geometry": {"type": "Point", "coordinates": [-119.61752319335938, 37.25510025024414]}}, {"type": "Feature", "id": 230, "properties": {"tag": "MeToo", "text": "RT @ScottRickhoff: Democrat Nobody Pete #Buttplug Accused of Sexual Assault by 21-Year-Old from Michigan. #Metoo #WalkAwayFromDemocrats #Wa\u2026"}, "geometry": {"type": "Point", "coordinates": [-92.8105697631836, 45.05670166015625]}}, {"type": "Feature", "id": 231, "properties": {"tag": "MeToo", "text": "Interesting that of your handful of likes, all but one are super supportive of Bernie and you have a whopping 1 act\u2026 https://t.co/kuXzwtnEBg"}, "geometry": {"type": "Point", "coordinates": [-89.64360046386719, 39.801048278808594]}}, {"type": "Feature", "id": 232, "properties": {"tag": "MeToo", "text": "Democrats allowed #MeToo to run untethered and unchecked when it benefited them. Anyone wanna place bets on how qui\u2026 https://t.co/0qE5IrmZMc"}, "geometry": {"type": "Point", "coordinates": [-91.1167984008789, 48.04707717895508]}}, {"type": "Feature", "id": 233, "properties": {"tag": "MeToo", "text": "RT @ScottRickhoff: Democrat Nobody Pete #Buttplug Accused of Sexual Assault by 21-Year-Old from Michigan. #Metoo #WalkAwayFromDemocrats #Wa\u2026"}, "geometry": {"type": "Point", "coordinates": [-83.4445571899414, 32.64833068847656]}}, {"type": "Feature", "id": 234, "properties": {"tag": "MeToo", "text": "RT @TheAbdullahKhan: First of all I think Shahzeb Khanzada deserves credit for conducting a highly professional interview with Meesha Shafi\u2026"}, "geometry": {"type": "Point", "coordinates": [73.07047271728516, 33.707679748535156]}}, {"type": "Feature", "id": 235, "properties": {"tag": "MeToo", "text": "RT @FullStopFdn: \"The underlying driver of sexual harassment in workplaces is power and the misuse of power, and because different workplac\u2026"}, "geometry": {"type": "Point", "coordinates": [144.53526306152344, -22.575700759887695]}}, {"type": "Feature", "id": 236, "properties": {"tag": "MeToo", "text": "@SuperPatriotone Wow, the #MeToo movement should be all over this.\n\nWhere is @Alyssa_Milano on this and did she ask\u2026 https://t.co/3FHTRnFdpd"}, "geometry": {"type": "Point", "coordinates": [-86.34304809570312, 35.84300231933594]}}, {"type": "Feature", "id": 237, "properties": {"tag": "MeToo", "text": "RT @FaerieWhings: A #MeToo story in the works.\n\nI hope Hunter heals. \n\nhttps://t.co/reIkzxTvt6"}, "geometry": {"type": "Point", "coordinates": [-118.472325, 34.2276600003532]}}, {"type": "Feature", "id": 238, "properties": {"tag": "MeToo", "text": "@darklordjournal @AspcraAdInferi Nah, not really. #MeToo"}, "geometry": {"type": "Point", "coordinates": [-150.05264282226562, 62.206478118896484]}}, {"type": "Feature", "id": 239, "properties": {"tag": "MeToo", "text": "Mayor Pete Hit With #MeToo Allegation of Sexual Assault https://t.co/M0tWnxJ9hw"}, "geometry": {"type": "Point", "coordinates": [-85.2876205444336, 37.5272331237793]}}, {"type": "Feature", "id": 240, "properties": {"tag": "MeToo", "text": "Democrat Nobody Pete #Buttplug Accused of Sexual Assault by 21-Year-Old from Michigan. #Metoo\u2026 https://t.co/SQ2K64c8tk"}, "geometry": {"type": "Point", "coordinates": [-98.98998260498047, 39.495914459228516]}}, {"type": "Feature", "id": 241, "properties": {"tag": "MeToo", "text": "RT @OGMurphy1: I AM ASHAMED BY BREXIT..\n\nThe way migrants were used as a scapegoat for our own government's economic failure;\n\nThe way chea\u2026"}, "geometry": {"type": "Point", "coordinates": [-2.5505640506744385, 53.9438362121582]}}, {"type": "Feature", "id": 242, "properties": {"tag": "MeToo", "text": "RT @ChatByCC: \u201cMy name is Hunter Kelly. I am 21 years old. I was sexually assaulted by Mayor Pete Buttigieg. I didn\u2019t know who he was back\u2026"}, "geometry": {"type": "Point", "coordinates": [-77.83875274658203, 40.89651107788086]}}, {"type": "Feature", "id": 243, "properties": {"tag": "MeToo", "text": "@gatewaypundit #metoo  - time to treat ol Pete like Kavanaugh"}, "geometry": {"type": "Point", "coordinates": [-85.73513793945312, 44.86261749267578]}}, {"type": "Feature", "id": 244, "properties": {"tag": "MeToo", "text": "RT @FreedomForumIns: \u201cIn late 2017 when #MeToo revelations exposed sexual harassment &amp; misconduct in many media organizations, we immediate\u2026"}, "geometry": {"type": "Point", "coordinates": [-89.73674011230469, 44.64178466796875]}}, {"type": "Feature", "id": 245, "properties": {"tag": "MeToo", "text": "@NickANigro @worldincommon @thesweatytuna @MrFesser @StarTribune The Vikings were known as rapists and pillagers wh\u2026 https://t.co/MG3wnKA4e6"}, "geometry": {"type": "Point", "coordinates": [-94.19837188720703, 46.34935760498047]}}, {"type": "Feature", "id": 246, "properties": {"tag": "MeToo", "text": "@diamondsnjeans @RonHall46 At last! An opportunity for me to say:\n\n     MeToo"}, "geometry": {"type": "Point", "coordinates": [-0.12721000611782074, 51.50642013549805]}}, {"type": "Feature", "id": 247, "properties": {"tag": "MeToo", "text": "Why people speaking in favour of PTM and Meesha shafi are the same ? "}, "geometry": {"type": "Point", "coordinates": [74.30348205566406, 31.53944969177246]}}, {"type": "Feature", "id": 248, "properties": {"tag": "MeToo", "text": "RT @ChatByCC: @Rockprincess818 \u201cMy name is Hunter Kelly. I am 21 years old. I was sexually assaulted by Mayor Pete Buttigieg. I didn\u2019t know\u2026"}, "geometry": {"type": "Point", "coordinates": [-119.61752319335938, 37.25510025024414]}}, {"type": "Feature", "id": 249, "properties": {"tag": "MeToo", "text": "RT @snowball1926: Here We go...True, not true?  Who are the @TheDemocrats going to believe.  What about the #MeToo movement?\n\n\"I was sexual\u2026"}, "geometry": {"type": "Point", "coordinates": [-99.3330307006836, 31.46275520324707]}}, {"type": "Feature", "id": 250, "properties": {"tag": "MeToo", "text": "RT @PrisonPlanet: Presidential candidate Mayor Pete Buttigieg is facing a potential #MeToo scandal after a Michigan man accused Buttigieg o\u2026"}, "geometry": {"type": "Point", "coordinates": [-98.98998260498047, 39.495914459228516]}}, {"type": "Feature", "id": 251, "properties": {"tag": "MeToo", "text": "@Maria_Memon @itsmeeshashafi Hahaha. This PTM and Metoo are tge new kewl to support"}, "geometry": {"type": "Point", "coordinates": [67.03437042236328, 24.92671012878418]}}, {"type": "Feature", "id": 252, "properties": {"tag": "MeToo", "text": "RT @EmHarriss: Whenever I hear men say, \u201cever since the #metoo era, we men have to be so careful\u201d .... I\u2019m like, be careful of what? Not ha\u2026"}, "geometry": {"type": "Point", "coordinates": [-2.4750399589538574, 52.7036018371582]}}, {"type": "Feature", "id": 253, "properties": {"tag": "MeToo", "text": "RT @ChatByCC: @Rockprincess818 \u201cMy name is Hunter Kelly. I am 21 years old. I was sexually assaulted by Mayor Pete Buttigieg. I didn\u2019t know\u2026"}, "geometry": {"type": "Point", "coordinates": [-79.18537902832031, 35.53935241699219]}}, {"type": "Feature", "id": 254, "properties": {"tag": "MeToo", "text": "RT @HtownDood: What do you make of this?\n#metoo?\nhttps://t.co/70LpXjeYvI"}, "geometry": {"type": "Point", "coordinates": [-99.3330307006836, 31.46275520324707]}}, {"type": "Feature", "id": 255, "properties": {"tag": "MeToo", "text": "Why women should have equal opportunities and rights in all countries worldwide: https://t.co/9dwQZEKSUv\n#feminism\u2026 https://t.co/FETc3z6GLk"}, "geometry": {"type": "Point", "coordinates": [26.282997131347656, 64.51988983154297]}}, {"type": "Feature", "id": 256, "properties": {"tag": "MeToo", "text": "\u2018MeToo\u2019 Hysteria: Handshakes In The Workplace Could Be Next On Chopping Block https://t.co/u7uvaWswxf"}, "geometry": {"type": "Point", "coordinates": [-119.61752319335938, 37.25510025024414]}}, {"type": "Feature", "id": 257, "properties": {"tag": "MeToo", "text": "RT @ChatByCC: @Rockprincess818 \u201cMy name is Hunter Kelly. I am 21 years old. I was sexually assaulted by Mayor Pete Buttigieg. I didn\u2019t know\u2026"}, "geometry": {"type": "Point", "coordinates": [-82.40010833740234, 34.848270416259766]}}, {"type": "Feature", "id": 258, "properties": {"tag": "MeToo", "text": "She says I'll check those msgs again ,wow chutyaa smjhaa hua hai awaam ko \nShe is fake Ali Zafar showed us proof wh\u2026 https://t.co/CWQer36z8m"}, "geometry": {"type": "Point", "coordinates": [68.80183410644531, 29.354202270507812]}}, {"type": "Feature", "id": 259, "properties": {"tag": "MeToo", "text": "RT @wkamaubell: The conversation w/ @emilyjoypoetry and her story of being abused in a megachurch that led her to create #ChurchToo (which\u2026"}, "geometry": {"type": "Point", "coordinates": [-83.53626251220703, 41.65380859375]}}]}